matching/__init__.py
matching/base.py
matching/exceptions.py
matching/matchings.py
matching/algorithms/__init__.py
matching/algorithms/hospital_resident.py
matching/algorithms/stable_marriage.py
matching/algorithms/stable_roommates.py
matching/algorithms/student_allocation.py
matching/algorithms/util.py
matching/games/__init__.py
matching/games/hospital_resident.py
matching/games/stable_marriage.py
matching/games/stable_roommates.py
matching/games/student_allocation.py
matching/players/__init__.py
matching/players/hospital.py
matching/players/player.py
matching/players/project.py
matching/players/supervisor.py
matching-1.4.3.dist-info/LICENSE
matching-1.4.3.dist-info/METADATA
matching-1.4.3.dist-info/WHEEL
matching-1.4.3.dist-info/top_level.txt
matching-1.4.3.dist-info/RECORD
