Metadata-Version: 2.1
Name: matching
Version: 1.4.3
Summary: A package for solving matching games
Author: Vince Knight
Author-email: Henry Wilde <henrydavidwilde@gmail.com>
License: MIT License
Project-URL: homepage, https://github.com/daffidwilde/matching
Project-URL: documentation, https://daffidwilde.github.io/matching
Project-URL: changelog, https://github.com/daffidwilde/matching/blob/main/CHANGES.md
Keywords: game-theory,gale-shapley,matching-games,stable-marriage,hospital-resident,stable-roommates,project-allocation
Classifier: Programming Language :: Python :: 3
Classifier: License :: OSI Approved :: MIT License
Classifier: Operating System :: OS Independent
Classifier: Intended Audience :: Science/Research
Classifier: Topic :: Scientific/Engineering :: Information Analysis
Requires-Python: >=3.5
License-File: LICENSE
Requires-Dist: numpy>=1.19.2
Provides-Extra: test
Requires-Dist: hypothesis>=6.31.6; extra == "test"
Requires-Dist: nbval>=0.10.0; extra == "test"
Requires-Dist: pytest>=6.2.5; extra == "test"
Requires-Dist: pytest-cov>=3.0.0; extra == "test"
Requires-Dist: pytest-randomly>=3.10; extra == "test"
Provides-Extra: docs
Requires-Dist: ipython>=7.10; extra == "docs"
Requires-Dist: matplotlib>=3; extra == "docs"
Requires-Dist: nbsphinx>=0.8.8; extra == "docs"
Requires-Dist: pandas>=1.1.5; extra == "docs"
Requires-Dist: PyYAML>=6; extra == "docs"
Requires-Dist: quartodoc>=0.5.0; python_version > "3.8" and extra == "docs"
Provides-Extra: dev
Requires-Dist: black[jupyter]<23,>=22.6.0; extra == "dev"
Requires-Dist: flake8>=4.0.1; extra == "dev"
Requires-Dist: interrogate>=1.5.0; extra == "dev"
Requires-Dist: isort>=5.10.1; extra == "dev"
Requires-Dist: matching[docs,test]; extra == "dev"
